{
    "Ax": {
        "error": 1.2535419125340105e-07,
        "error_type": "SEM",
        "filter_outliers_dict": {
            "filter_outliers": true,
            "iterations": 1,
            "std_devs": 2,
            "use_iqr_filtering": false,
            "use_standard_deviation_filtering": true
        },
        "fit": "average",
        "fn": 49,
        "include_baseline_error": false,
        "n": 50,
        "outlier_excluded": [
            15
        ],
        "reviewed": true,
        "user_excluded": [],
        "value": -8.936916086041696e-06
    },
    "H2": {
        "error": 8.667180844337372e-08,
        "error_type": "SEM",
        "filter_outliers_dict": {
            "filter_outliers": true,
            "iterations": 1,
            "std_devs": 2,
            "use_iqr_filtering": false,
            "use_standard_deviation_filtering": true
        },
        "fit": "average",
        "fn": 47,
        "include_baseline_error": false,
        "n": 50,
        "outlier_excluded": [
            9,
            28,
            21
        ],
        "reviewed": true,
        "user_excluded": [],
        "value": -5.907779365209516e-06
    },
    "H4": {
        "error": 8.059494976696776e-08,
        "error_type": "SEM",
        "filter_outliers_dict": {
            "filter_outliers": true,
            "iterations": 1,
            "std_devs": 2,
            "use_iqr_filtering": false,
            "use_standard_deviation_filtering": true
        },
        "fit": "average",
        "fn": 48,
        "include_baseline_error": false,
        "n": 50,
        "outlier_excluded": [
            19,
            29
        ],
        "reviewed": true,
        "user_excluded": [],
        "value": -5.765586507777698e-06
    },
    "L2": {
        "error": 7.375567214875958e-08,
        "error_type": "SEM",
        "filter_outliers_dict": {
            "filter_outliers": true,
            "iterations": 1,
            "std_devs": 2,
            "use_iqr_filtering": false,
            "use_standard_deviation_filtering": true
        },
        "fit": "average",
        "fn": 44,
        "include_baseline_error": false,
        "n": 50,
        "outlier_excluded": [
            32,
            36,
            40,
            9,
            16,
            17
        ],
        "reviewed": true,
        "user_excluded": [],
        "value": -1.0045216868093121e-05
    },
    "L4": {
        "error": 9.984800581227464e-09,
        "error_type": "SEM",
        "filter_outliers_dict": {
            "filter_outliers": true,
            "iterations": 1,
            "std_devs": 2,
            "use_iqr_filtering": false,
            "use_standard_deviation_filtering": true
        },
        "fit": "average",
        "fn": 49,
        "include_baseline_error": false,
        "n": 50,
        "outlier_excluded": [
            22
        ],
        "reviewed": true,
        "user_excluded": [],
        "value": 3.807346946378319e-07
    }
}